<definitions ECU="2018">
<ecuparam id="1" name="AF Correction 1" desc="P1">
	<address length="3">00 00 09</address>
	<response length="1">04</response>
	<conversions>
		<conversion units="%" expr="0.78125" format="0.00"/>
		<offset>-100</offset>
	</conversions>
</ecuparam>
<ecuparam id="2" name="AF Learning 1" desc="P2">
	<address length="3">00 00 0A</address>
	<response length="1">04</response>
	<conversions>
		<conversion units="%" expr="0.78125" format="0.00"/>
		<offset>-100</offset>
	</conversions>
</ecuparam>
<ecuparam id="3" name="AF Ratio" desc="P3">
	<address length="6">F8 8E D8 F8 8E D9</address>
	<response length="2">05</response>
	<conversions>
		<conversion units="AFR" expr="0.00179" format="0.00" />
		<offset>0</offset>
	</conversions>
</ecuparam>
<ecuparam id="4" name="Battery" desc="P4">
	<address length="4">00 00 1C</address>
	<response length="2">04</response>
	<conversions>
		<conversion units="Volts" expr="0.08" format="0.00" />
		<offset>0</offset>
	</conversions>
</ecuparam>
<ecuparam id="5" name="Boost" desc="P5">
	<address length="9">F8 3C 6A F8 3C 6B 00 00 23</address>
	<response length="3">06</response>
	<conversions>
		<conversion units="psi" expr="6451.6129" format="0" invert="1"/>
		<offset>-14.65</offset>
	</conversions>
</ecuparam>
<ecuparam id="6" name="Command Fuel Final" desc="P6">
	<address length="6">F8 C4 0A F8 C4 0B</address>
	<response length="2">05</response>
	<conversions>
		<conversion units="AFR" expr="3763.2" format="0.00" invert="1"/>
		<offset>0</offset>
	</conversions>
</ecuparam>
<ecuparam id="7" name="Dynamic Advance Multiplier" desc="P7">
	<address length="3">F8 11 00</address>
	<response length="1">04</response>
	<conversions>
		<conversion units="x" expr="0.0625" format="0.0" />
		<offset>0</offset>
	</conversions>
</ecuparam>
<ecuparam id="8" name="Feedback Knock Correction" desc="P8">
	<address length="6">F8 BB CA</address>
	<response length="1">04</response>
	<conversions>
		<conversion units="degrees" expr="0.3515625" format="0.00" />
		<offset>0</offset>
	</conversions>
</ecuparam>
<ecuparam id="9" name="Fine Knock Learn" desc="P9">
	<address length="6">F8 BB DA</address>
	<response length="1">04</response>
	<conversions>
		<conversion units="degrees" expr="0.3515625" format="0.00" />
		<offset>0</offset>
	</conversions>
</ecuparam>
<ecuparam id="10" name="Fuel Pressure" desc="P10">
	<address length="6">F8 8C 64 F8 8C 65</address>
	<response length="2">04</response>
	<conversions>
		<conversion units="psi" expr="0.10" format="0" />
		<offset>0</offset>
	</conversions>
</ecuparam>
<ecuparam id="11" name="Gear Position" desc="P11">
	<address length="6">F8 8E D8 F8 8E D9</address>
	<response length="2">04</response>
	<conversions>
		<conversion units="gear" expr="1" format="0" />
		<offset>1</offset>
	</conversions>
</ecuparam>
<ecuparam id="12" name="Injector Duty" desc="P12">
	<address length="6">00002000000E00000F</address>
	<response length="3">06</response>
	<conversions>
		<conversion units="%" expr="0.000000006297" format="0.00" />
		<offset>-0.5321</offset>
	</conversions>
</ecuparam>
<ecuparam id="13" name="Calculated Load" desc="P13">
	<address length="6">F8BA26</address>
	<response length="1">04</response>
	<conversions>
		<conversion units="g/rev" expr="0.01294" format="0.00" />
		<offset>0</offset>
	</conversions>
</ecuparam>
<ecuparam id="14" name="Intake Manifold Temperature" desc="P14">
	<address length="6">F8 8C B4</address>
	<response length="1">04</response>
	<conversions>
		<conversion units="F" expr="1.8" format="0" />
		<offset>-57.8</offset>
	</conversions>
</ecuparam>
<ecuparam id="15" name="Vehicle Speed" desc="P15">
	<address length="6">000010</address>
	<response length="1">04</response>
	<conversions>
		<conversion units="mph" expr="0.621371192" format="0"/>
		<offset>0</offset>
	</conversions>
</ecuparam>
<ecuparam id="16" name="Ignition  Timing" desc="P16">
	<address length="6">000011</address>
	<response length="1">04</response>
	<conversions>
		<conversion units="degrees" expr="0.5" format="0.00"/>
		<offset>-64</offset>
	</conversions>
</ecuparam>
<ecuparam id="17" name="Wastegate Duty Cycle" desc="P17">
	<address length="6">000030</address>
	<response length="1">04</response>
	<conversions>
		<conversion units="%" expr="0.039092" format="0.00" />
		<offset>0</offset>
	</conversions>
</ecuparam>
<ecuparam id="18" name="Engine Speed" desc="P18">
	<address length="1">F8E3D4F8E3D5</address>
	<response length="2">04</response>
	<conversions>
		<conversion units="rpm" expr="0.2" format="0" />
		<offset>0</offset>
	</conversions>
</ecuparam>
<ecuparam id="19" name="Injector Pulse Width" desc="P19">
	<address length="6">F8E5BCF8E5BD</address>
	<response length="2">06</response>
	<conversions>
		<conversion units="ms" expr="0.0034" format="0.00" />
		<offset>-0.0789</offset>
	</conversions>
</ecuparam>
<ecuparam id="20" name="Atmospheric Pressure" desc="P20">
	<address length="3">00 00 23</address>
	<response length="1">06</response>
	<conversions>
		<conversion units="psi" expr="0.1451" format="0" />
		<offset>0</offset>
	</conversions>
</ecuparam>
<ecuparam id="21" name="Manifold Absolute Pressure" desc="P21">
	<address length="9">F8 3C 6A F8 3C 6B</address>
	<response length="2">06</response>
	<conversions>
		<conversion units="psi" expr="6451.6129" format="0" invert="1"/>
		<offset>0</offset>
	</conversions>
</ecuparam>
</definitions>
